cltrier_nlp/__init__.py
cltrier_nlp/corpus/__init__.py
cltrier_nlp/corpus/sentence.py
cltrier_nlp/encoder/__init__.py
cltrier_nlp/encoder/batch.py
cltrier_nlp/encoder/pooler.py
cltrier_nlp/functional/__init__.py
cltrier_nlp/functional/neural.py
cltrier_nlp/functional/text.py
cltrier_nlp/trainer/__init__.py
cltrier_nlp/trainer/metric.py
cltrier_nlp/trainer/progress.py
cltrier_nlp/utility/__init__.py
cltrier_nlp/utility/map.py
cltrier_nlp/utility/types.py
cltrier_nlp-0.1.8.dist-info/LICENSE
cltrier_nlp-0.1.8.dist-info/METADATA
cltrier_nlp-0.1.8.dist-info/WHEEL
cltrier_nlp-0.1.8.dist-info/RECORD
