Metadata-Version: 2.1
Name: cltrier_nlp
Version: 0.1.8
Summary: 
Home-page: https://github.com/simon-muenker/cltrier_nlp
License: Apache-2.0
Author: Simon Münker
Author-email: muenker@uni-trier.de
Requires-Python: >=3.10,<4.0
Classifier: Development Status :: 3 - Alpha
Classifier: Intended Audience :: Science/Research
Classifier: License :: OSI Approved :: Apache Software License
Classifier: Programming Language :: Python :: 3
Classifier: Programming Language :: Python :: 3.10
Classifier: Programming Language :: Python :: 3.11
Classifier: Programming Language :: Python :: 3.12
Classifier: Topic :: Text Processing
Requires-Dist: langcodes (>=3.4.0,<4.0.0)
Requires-Dist: langdetect (>=1.0.9,<2.0.0)
Requires-Dist: nltk (>=3.8.1,<4.0.0)
Requires-Dist: pydantic (>=2.7.1,<3.0.0)
Requires-Dist: torch (>=2.2.2,<3.0.0)
Requires-Dist: transformers (>=4.40.1,<5.0.0)
Project-URL: Documentation, https://simon-muenker.github.io/cltrier_nlp/
Project-URL: Repository, https://github.com/simon-muenker/cltrier_nlp
